<?xml version="1.0" ?>
<knowtator-project>
   <document id="PMC1280409.nxml.gz" text-file="PMC1280409.nxml.gz.txt">
      <annotation annotator="Default" id="PMC1280409.nxml.gz-1" type="identity">
         <class id="unknown"/>
         <span end="1053" id="PMC1280409.nxml.gz-2" start="1046">unknown</span>
      </annotation>
      <annotation annotator="Default" id="PMC1280409.nxml.gz-3" type="identity">
         <class id="unsuccessful"/>
         <span end="2512" id="PMC1280409.nxml.gz-4" start="2500">unsuccessful</span>
      </annotation>
      <annotation annotator="Default" id="PMC1280409.nxml.gz-5" type="identity">
         <class id="difficult"/>
         <span end="3712" id="PMC1280409.nxml.gz-6" start="3703">difficult</span>
      </annotation>
      <annotation annotator="Default" id="PMC1280409.nxml.gz-7" type="identity">
         <class id="difficult"/>
         <span end="3945" id="PMC1280409.nxml.gz-8" start="3936">difficult</span>
      </annotation>
      <annotation annotator="Default" id="PMC1280409.nxml.gz-9" type="identity">
         <class id="complicated"/>
         <span end="4452" id="PMC1280409.nxml.gz-10" start="4441">complicated</span>
      </annotation>
      <annotation annotator="Default" id="PMC1280409.nxml.gz-11" type="identity">
         <class id="difficult_task"/>
         <span end="4892" id="PMC1280409.nxml.gz-12" start="4878">multifactorial</span>
      </annotation>
      <annotation annotator="Default" id="PMC1280409.nxml.gz-13" type="identity">
         <class id="difficulties"/>
         <span end="12478" id="PMC1280409.nxml.gz-14" start="12466">difficulties</span>
      </annotation>
      <annotation annotator="Default" id="PMC1280409.nxml.gz-15" type="identity">
         <class id="difficulties"/>
         <span end="15960" id="PMC1280409.nxml.gz-16" start="15948">difficulties</span>
      </annotation>
      <annotation annotator="Default" id="PMC1280409.nxml.gz-17" type="identity">
         <class id="difficult"/>
         <span end="18773" id="PMC1280409.nxml.gz-18" start="18764">difficult</span>
      </annotation>
      <annotation annotator="Default" id="PMC1280409.nxml.gz-19" type="identity">
         <class id="impossible"/>
         <span end="20739" id="PMC1280409.nxml.gz-20" start="20729">impossible</span>
      </annotation>
      <annotation annotator="Default" id="PMC1280409.nxml.gz-21" type="identity">
         <class id="how"/>
         <span end="5577" id="PMC1280409.nxml.gz-22" start="5574">how</span>
      </annotation>
      <annotation annotator="Default" id="PMC1280409.nxml.gz-23" type="identity">
         <class id="several_studies"/>
         <span end="170" id="PMC1280409.nxml.gz-24" start="155">Several studies</span>
      </annotation>
      <annotation annotator="Default" id="PMC1280409.nxml.gz-25" type="identity">
         <class id="may"/>
         <span end="262" id="PMC1280409.nxml.gz-26" start="259">may</span>
      </annotation>
      <annotation annotator="Default" id="PMC1280409.nxml.gz-27" type="identity">
         <class id="preliminary_evidence"/>
         <span end="376" id="PMC1280409.nxml.gz-28" start="356">Preliminary evidence</span>
      </annotation>
      <annotation annotator="Default" id="PMC1280409.nxml.gz-29" type="identity">
         <class id="suggesting"/>
         <span end="421" id="PMC1280409.nxml.gz-30" start="411">suggesting</span>
      </annotation>
      <annotation annotator="Default" id="PMC1280409.nxml.gz-31" type="identity">
         <class id="may"/>
         <span end="474" id="PMC1280409.nxml.gz-32" start="471">may</span>
      </annotation>
      <annotation annotator="Default" id="PMC1280409.nxml.gz-33" type="identity">
         <class id="incomplete_evidence"/>
         <span end="540" id="PMC1280409.nxml.gz-34" start="537">has</span>
      </annotation>
      <annotation annotator="Default" id="PMC1280409.nxml.gz-35" type="identity">
         <class id="some"/>
         <span end="649" id="PMC1280409.nxml.gz-36" start="645">some</span>
      </annotation>
      <annotation annotator="Default" id="PMC1280409.nxml.gz-37" type="identity">
         <class id="have_been"/>
         <span end="667" id="PMC1280409.nxml.gz-38" start="658">have been</span>
      </annotation>
      <annotation annotator="Default" id="PMC1280409.nxml.gz-39" type="identity">
         <class id="described"/>
         <span end="677" id="PMC1280409.nxml.gz-40" start="668">described</span>
      </annotation>
      <annotation annotator="Default" id="PMC1280409.nxml.gz-41" type="identity">
         <class id="theorized"/>
         <span end="1292" id="PMC1280409.nxml.gz-42" start="1283">theorized</span>
      </annotation>
      <annotation annotator="Default" id="PMC1280409.nxml.gz-43" type="identity">
         <class id="may"/>
         <span end="1367" id="PMC1280409.nxml.gz-44" start="1364">may</span>
      </annotation>
      <annotation annotator="Default" id="PMC1280409.nxml.gz-45" type="identity">
         <class id="hypothesis"/>
         <span end="1457" id="PMC1280409.nxml.gz-46" start="1447">hypothesis</span>
      </annotation>
      <annotation annotator="Default" id="PMC1280409.nxml.gz-47" type="identity">
         <class id="hypothesis"/>
         <span end="1734" id="PMC1280409.nxml.gz-48" start="1724">hypothesis</span>
      </annotation>
      <annotation annotator="Default" id="PMC1280409.nxml.gz-49" type="identity">
         <class id="incomplete_evidence"/>
         <span end="1807" id="PMC1280409.nxml.gz-50" start="1800">ongoing</span>
      </annotation>
      <annotation annotator="Default" id="PMC1280409.nxml.gz-51" type="identity">
         <class id="incomplete_evidence"/>
         <span end="2078" id="PMC1280409.nxml.gz-52" start="2075">has</span>
      </annotation>
      <annotation annotator="Default" id="PMC1280409.nxml.gz-53" type="identity">
         <class id="incomplete_evidence"/>
         <span end="2347" id="PMC1280409.nxml.gz-54" start="2344">For</span>
      </annotation>
      <annotation annotator="Default" id="PMC1280409.nxml.gz-55" type="identity">
         <class id="incomplete_evidence"/>
         <span end="2357" id="PMC1280409.nxml.gz-56" start="2348">some time</span>
      </annotation>
      <annotation annotator="Default" id="PMC1280409.nxml.gz-57" type="identity">
         <class id="incomplete_evidence"/>
         <span end="2388" id="PMC1280409.nxml.gz-58" start="2383">doubt</span>
      </annotation>
      <annotation annotator="Default" id="PMC1280409.nxml.gz-59" type="identity">
         <class id="many"/>
         <span end="2447" id="PMC1280409.nxml.gz-60" start="2443">Many</span>
      </annotation>
      <annotation annotator="Default" id="PMC1280409.nxml.gz-61" type="identity">
         <class id="evidence"/>
         <span end="2471" id="PMC1280409.nxml.gz-62" start="2463">evidence</span>
      </annotation>
      <annotation annotator="Default" id="PMC1280409.nxml.gz-63" type="identity">
         <class id="suggested"/>
         <span end="2743" id="PMC1280409.nxml.gz-64" start="2734">suggested</span>
      </annotation>
      <annotation annotator="Default" id="PMC1280409.nxml.gz-65" type="identity">
         <class id="found"/>
         <span end="2873" id="PMC1280409.nxml.gz-66" start="2868">found</span>
      </annotation>
      <annotation annotator="Default" id="PMC1280409.nxml.gz-67" type="identity">
         <class id="suggest"/>
         <span end="3027" id="PMC1280409.nxml.gz-68" start="3020">suggest</span>
      </annotation>
      <annotation annotator="Default" id="PMC1280409.nxml.gz-69" type="identity">
         <class id="have_been"/>
         <span end="3242" id="PMC1280409.nxml.gz-70" start="3233">have been</span>
      </annotation>
      <annotation annotator="Default" id="PMC1280409.nxml.gz-71" type="identity">
         <class id="findings"/>
         <span end="3274" id="PMC1280409.nxml.gz-72" start="3266">findings</span>
      </annotation>
      <annotation annotator="Default" id="PMC1280409.nxml.gz-73" type="identity">
         <class id="indicate"/>
         <span end="3341" id="PMC1280409.nxml.gz-74" start="3333">indicate</span>
      </annotation>
      <annotation annotator="Default" id="PMC1280409.nxml.gz-75" type="identity">
         <class id="incomplete_evidence"/>
         <span end="3998" id="PMC1280409.nxml.gz-76" start="3990">reliable</span>
      </annotation>
      <annotation annotator="Default" id="PMC1280409.nxml.gz-77" type="identity">
         <class id="evidence"/>
         <span end="4007" id="PMC1280409.nxml.gz-78" start="3999">evidence</span>
      </annotation>
      <annotation annotator="Default" id="PMC1280409.nxml.gz-79" type="identity">
         <class id="potential"/>
         <span end="4124" id="PMC1280409.nxml.gz-80" start="4115">potential</span>
      </annotation>
      <annotation annotator="Default" id="PMC1280409.nxml.gz-81" type="identity">
         <class id="may"/>
         <span end="4518" id="PMC1280409.nxml.gz-82" start="4515">may</span>
      </annotation>
      <annotation annotator="Default" id="PMC1280409.nxml.gz-83" type="identity">
         <class id="recent"/>
         <span end="4930" id="PMC1280409.nxml.gz-84" start="4924">Recent</span>
      </annotation>
      <annotation annotator="Default" id="PMC1280409.nxml.gz-85" type="identity">
         <class id="have_been"/>
         <span end="5273" id="PMC1280409.nxml.gz-86" start="5264">have been</span>
      </annotation>
      <annotation annotator="Default" id="PMC1280409.nxml.gz-87" type="identity">
         <class id="number_of_studies"/>
         <span end="5307" id="PMC1280409.nxml.gz-88" start="5290">number of studies</span>
      </annotation>
      <annotation annotator="Default" id="PMC1280409.nxml.gz-89" type="identity">
         <class id="suggestive"/>
         <span end="5332" id="PMC1280409.nxml.gz-90" start="5322">suggestive</span>
      </annotation>
      <annotation annotator="Default" id="PMC1280409.nxml.gz-91" type="identity">
         <class id="describe"/>
         <span end="5368" id="PMC1280409.nxml.gz-92" start="5360">describe</span>
      </annotation>
      <annotation annotator="Default" id="PMC1280409.nxml.gz-93" type="identity">
         <class id="incomplete_evidence"/>
         <span end="5372" id="PMC1280409.nxml.gz-94" start="5369">one</span>
      </annotation>
      <annotation annotator="Default" id="PMC1280409.nxml.gz-95" type="identity">
         <class id="incomplete_evidence"/>
         <span end="5386" id="PMC1280409.nxml.gz-96" start="5373">ongoing study</span>
      </annotation>
      <annotation annotator="Default" id="PMC1280409.nxml.gz-97" type="identity">
         <class id="incomplete_evidence"/>
         <span end="5597" id="PMC1280409.nxml.gz-98" start="5593">been</span>
      </annotation>
      <annotation annotator="Default" id="PMC1280409.nxml.gz-99" type="identity">
         <class id="have_been"/>
         <span end="6180" id="PMC1280409.nxml.gz-100" start="6171">have been</span>
      </annotation>
      <annotation annotator="Default" id="PMC1280409.nxml.gz-101" type="identity">
         <class id="previous"/>
         <span end="7091" id="PMC1280409.nxml.gz-102" start="7083">Previous</span>
      </annotation>
      <annotation annotator="Default" id="PMC1280409.nxml.gz-103" type="identity">
         <class id="has_been"/>
         <span end="7184" id="PMC1280409.nxml.gz-104" start="7176">has been</span>
      </annotation>
      <annotation annotator="Default" id="PMC1280409.nxml.gz-105" type="identity">
         <class id="incomplete_evidence"/>
         <span end="7195" id="PMC1280409.nxml.gz-106" start="7185">considered</span>
      </annotation>
      <annotation annotator="Default" id="PMC1280409.nxml.gz-107" type="identity">
         <class id="for_some_time"/>
         <span end="7209" id="PMC1280409.nxml.gz-108" start="7196">for some time</span>
      </annotation>
      <annotation annotator="Default" id="PMC1280409.nxml.gz-109" type="identity">
         <class id="incomplete_evidence"/>
         <span end="7343" id="PMC1280409.nxml.gz-110" start="7330">first studies</span>
      </annotation>
      <annotation annotator="Default" id="PMC1280409.nxml.gz-111" type="identity">
         <class id="usually"/>
         <span end="7760" id="PMC1280409.nxml.gz-112" start="7753">usually</span>
      </annotation>
      <annotation annotator="Default" id="PMC1280409.nxml.gz-113" type="identity">
         <class id="demonstrated"/>
         <span end="8126" id="PMC1280409.nxml.gz-114" start="8114">demonstrated</span>
      </annotation>
      <annotation annotator="Default" id="PMC1280409.nxml.gz-115" type="identity">
         <class id="showed"/>
         <span end="8354" id="PMC1280409.nxml.gz-116" start="8348">showed</span>
      </annotation>
      <annotation annotator="Default" id="PMC1280409.nxml.gz-117" type="identity">
         <class id="usually"/>
         <span end="8420" id="PMC1280409.nxml.gz-118" start="8413">usually</span>
      </annotation>
      <annotation annotator="Default" id="PMC1280409.nxml.gz-119" type="identity">
         <class id="only"/>
         <span end="8552" id="PMC1280409.nxml.gz-120" start="8548">only</span>
      </annotation>
      <annotation annotator="Default" id="PMC1280409.nxml.gz-121" type="identity">
         <class id="previous"/>
         <span end="9172" id="PMC1280409.nxml.gz-122" start="9164">previous</span>
      </annotation>
      <annotation annotator="Default" id="PMC1280409.nxml.gz-123" type="identity">
         <class id="limitations"/>
         <span end="9218" id="PMC1280409.nxml.gz-124" start="9207">limitations</span>
      </annotation>
      <annotation annotator="Default" id="PMC1280409.nxml.gz-125" type="identity">
         <class id="small"/>
         <span end="9314" id="PMC1280409.nxml.gz-126" start="9309">small</span>
      </annotation>
      <annotation annotator="Default" id="PMC1280409.nxml.gz-127" type="identity">
         <class id="found"/>
         <span end="9383" id="PMC1280409.nxml.gz-128" start="9378">found</span>
      </annotation>
      <annotation annotator="Default" id="PMC1280409.nxml.gz-129" type="identity">
         <class id="incomplete_evidence"/>
         <span end="9773" id="PMC1280409.nxml.gz-130" start="9756">previous findings</span>
      </annotation>
      <annotation annotator="Default" id="PMC1280409.nxml.gz-131" type="identity">
         <class id="incomplete_evidence"/>
         <span end="9810" id="PMC1280409.nxml.gz-132" start="9805">Prior</span>
      </annotation>
      <annotation annotator="Default" id="PMC1280409.nxml.gz-133" type="identity">
         <class id="indicated"/>
         <span end="9833" id="PMC1280409.nxml.gz-134" start="9824">indicated</span>
      </annotation>
      <annotation annotator="Default" id="PMC1280409.nxml.gz-135" type="identity">
         <class id="has...been"/>
         <span end="10135" id="PMC1280409.nxml.gz-136" start="10132">has</span>
         <span end="10145" id="PMC1280409.nxml.gz-137" start="10141">been</span>
      </annotation>
      <annotation annotator="Default" id="PMC1280409.nxml.gz-138" type="identity">
         <class id="postulated"/>
         <span end="10156" id="PMC1280409.nxml.gz-139" start="10146">postulated</span>
      </annotation>
      <annotation annotator="Default" id="PMC1280409.nxml.gz-140" type="identity">
         <class id="have_been"/>
         <span end="10288" id="PMC1280409.nxml.gz-141" start="10279">have been</span>
      </annotation>
      <annotation annotator="Default" id="PMC1280409.nxml.gz-142" type="identity">
         <class id="previously"/>
         <span end="10299" id="PMC1280409.nxml.gz-143" start="10289">previously</span>
      </annotation>
      <annotation annotator="Default" id="PMC1280409.nxml.gz-144" type="identity">
         <class id="incomplete_evidence"/>
         <span end="10404" id="PMC1280409.nxml.gz-145" start="10401">one</span>
      </annotation>
      <annotation annotator="Default" id="PMC1280409.nxml.gz-146" type="identity">
         <class id="incomplete_evidence"/>
         <span end="10419" id="PMC1280409.nxml.gz-147" start="10405">landmark study</span>
      </annotation>
      <annotation annotator="Default" id="PMC1280409.nxml.gz-148" type="identity">
         <class id="incomplete_evidence"/>
         <span end="10855" id="PMC1280409.nxml.gz-149" start="10852">not</span>
      </annotation>
      <annotation annotator="Default" id="PMC1280409.nxml.gz-150" type="identity">
         <class id="incomplete_evidence"/>
         <span end="10870" id="PMC1280409.nxml.gz-151" start="10857">Later studies</span>
      </annotation>
      <annotation annotator="Default" id="PMC1280409.nxml.gz-152" type="identity">
         <class id="these_findings"/>
         <span end="10899" id="PMC1280409.nxml.gz-153" start="10885">these findings</span>
      </annotation>
      <annotation annotator="Default" id="PMC1280409.nxml.gz-154" type="identity">
         <class id="showed"/>
         <span end="10959" id="PMC1280409.nxml.gz-155" start="10953">showed</span>
      </annotation>
      <annotation annotator="Default" id="PMC1280409.nxml.gz-156" type="identity">
         <class id="studies"/>
         <span end="11064" id="PMC1280409.nxml.gz-157" start="11057">studies</span>
      </annotation>
      <annotation annotator="Default" id="PMC1280409.nxml.gz-158" type="identity">
         <class id="found_evidence"/>
         <span end="11079" id="PMC1280409.nxml.gz-159" start="11065">found evidence</span>
      </annotation>
      <annotation annotator="Default" id="PMC1280409.nxml.gz-160" type="identity">
         <class id="recently"/>
         <span end="11222" id="PMC1280409.nxml.gz-161" start="11214">Recently</span>
      </annotation>
      <annotation annotator="Default" id="PMC1280409.nxml.gz-162" type="identity">
         <class id="finding"/>
         <span end="11765" id="PMC1280409.nxml.gz-163" start="11758">finding</span>
      </annotation>
      <annotation annotator="Default" id="PMC1280409.nxml.gz-164" type="identity">
         <class id="has_been"/>
         <span end="11935" id="PMC1280409.nxml.gz-165" start="11927">has been</span>
      </annotation>
      <annotation annotator="Default" id="PMC1280409.nxml.gz-166" type="identity">
         <class id="recently"/>
         <span end="11976" id="PMC1280409.nxml.gz-167" start="11968">recently</span>
      </annotation>
      <annotation annotator="Default" id="PMC1280409.nxml.gz-168" type="identity">
         <class id="has_been"/>
         <span end="11985" id="PMC1280409.nxml.gz-169" start="11977">has been</span>
      </annotation>
      <annotation annotator="Default" id="PMC1280409.nxml.gz-170" type="identity">
         <class id="stated"/>
         <span end="12067" id="PMC1280409.nxml.gz-171" start="12061">stated</span>
      </annotation>
      <annotation annotator="Default" id="PMC1280409.nxml.gz-172" type="identity">
         <class id="usually"/>
         <span end="12124" id="PMC1280409.nxml.gz-173" start="12117">usually</span>
      </annotation>
      <annotation annotator="Default" id="PMC1280409.nxml.gz-174" type="identity">
         <class id="small"/>
         <span end="12399" id="PMC1280409.nxml.gz-175" start="12394">small</span>
      </annotation>
      <annotation annotator="Default" id="PMC1280409.nxml.gz-176" type="identity">
         <class id="initial_studies"/>
         <span end="12517" id="PMC1280409.nxml.gz-177" start="12502">initial studies</span>
      </annotation>
      <annotation annotator="Default" id="PMC1280409.nxml.gz-178" type="identity">
         <class id="has_been"/>
         <span end="12548" id="PMC1280409.nxml.gz-179" start="12540">has been</span>
      </annotation>
      <annotation annotator="Default" id="PMC1280409.nxml.gz-180" type="identity">
         <class id="indicate"/>
         <span end="12732" id="PMC1280409.nxml.gz-181" start="12724">indicate</span>
      </annotation>
      <annotation annotator="Default" id="PMC1280409.nxml.gz-182" type="identity">
         <class id="have_been"/>
         <span end="12892" id="PMC1280409.nxml.gz-183" start="12883">have been</span>
      </annotation>
      <annotation annotator="Default" id="PMC1280409.nxml.gz-184" type="identity">
         <class id="number_of"/>
         <span end="12912" id="PMC1280409.nxml.gz-185" start="12903">number of</span>
      </annotation>
      <annotation annotator="Default" id="PMC1280409.nxml.gz-186" type="identity">
         <class id="these_studies"/>
         <span end="13157" id="PMC1280409.nxml.gz-187" start="13144">These studies</span>
      </annotation>
      <annotation annotator="Default" id="PMC1280409.nxml.gz-188" type="identity">
         <class id="support"/>
         <span end="13207" id="PMC1280409.nxml.gz-189" start="13200">support</span>
      </annotation>
      <annotation annotator="Default" id="PMC1280409.nxml.gz-190" type="identity">
         <class id="informative"/>
         <span end="13385" id="PMC1280409.nxml.gz-191" start="13374">informative</span>
      </annotation>
      <annotation annotator="Default" id="PMC1280409.nxml.gz-192" type="identity">
         <class id="few...studies"/>
         <span end="13446" id="PMC1280409.nxml.gz-193" start="13443">few</span>
         <span end="13469" id="PMC1280409.nxml.gz-194" start="13462">studies</span>
      </annotation>
      <annotation annotator="Default" id="PMC1280409.nxml.gz-195" type="identity">
         <class id="showed"/>
         <span end="14215" id="PMC1280409.nxml.gz-196" start="14209">showed</span>
      </annotation>
      <annotation annotator="Default" id="PMC1280409.nxml.gz-197" type="identity">
         <class id="show"/>
         <span end="14642" id="PMC1280409.nxml.gz-198" start="14638">show</span>
      </annotation>
      <annotation annotator="Default" id="PMC1280409.nxml.gz-199" type="identity">
         <class id="estimated"/>
         <span end="15286" id="PMC1280409.nxml.gz-200" start="15277">estimated</span>
      </annotation>
      <annotation annotator="Default" id="PMC1280409.nxml.gz-201" type="identity">
         <class id="reported"/>
         <span end="15417" id="PMC1280409.nxml.gz-202" start="15409">reported</span>
      </annotation>
      <annotation annotator="Default" id="PMC1280409.nxml.gz-203" type="identity">
         <class id="findings"/>
         <span end="15758" id="PMC1280409.nxml.gz-204" start="15750">Findings</span>
      </annotation>
      <annotation annotator="Default" id="PMC1280409.nxml.gz-205" type="identity">
         <class id="many"/>
         <span end="15807" id="PMC1280409.nxml.gz-206" start="15803">Many</span>
      </annotation>
      <annotation annotator="Default" id="PMC1280409.nxml.gz-207" type="identity">
         <class id="described"/>
         <span end="15832" id="PMC1280409.nxml.gz-208" start="15823">described</span>
      </annotation>
      <annotation annotator="Default" id="PMC1280409.nxml.gz-209" type="identity">
         <class id="comparable"/>
         <span end="15975" id="PMC1280409.nxml.gz-210" start="15965">comparable</span>
      </annotation>
      <annotation annotator="Default" id="PMC1280409.nxml.gz-211" type="identity">
         <class id="number_of"/>
         <span end="16034" id="PMC1280409.nxml.gz-212" start="16025">number of</span>
      </annotation>
      <annotation annotator="Default" id="PMC1280409.nxml.gz-213" type="identity">
         <class id="incomplete_evidence"/>
         <span end="16067" id="PMC1280409.nxml.gz-214" start="16048">have been suggested</span>
      </annotation>
      <annotation annotator="Default" id="PMC1280409.nxml.gz-215" type="identity">
         <class id="have...been"/>
         <span end="16135" id="PMC1280409.nxml.gz-216" start="16131">have</span>
         <span end="16145" id="PMC1280409.nxml.gz-217" start="16141">been</span>
      </annotation>
      <annotation annotator="Default" id="PMC1280409.nxml.gz-218" type="identity">
         <class id="suggestive"/>
         <span end="16315" id="PMC1280409.nxml.gz-219" start="16305">suggestive</span>
      </annotation>
      <annotation annotator="Default" id="PMC1280409.nxml.gz-220" type="identity">
         <class id="may_be"/>
         <span end="16372" id="PMC1280409.nxml.gz-221" start="16366">may be</span>
      </annotation>
      <annotation annotator="Default" id="PMC1280409.nxml.gz-222" type="identity">
         <class id="incomplete_evidence"/>
         <span end="16388" id="PMC1280409.nxml.gz-223" start="16383">model</span>
      </annotation>
      <annotation annotator="Default" id="PMC1280409.nxml.gz-224" type="identity">
         <class id="several"/>
         <span end="16626" id="PMC1280409.nxml.gz-225" start="16619">several</span>
      </annotation>
      <annotation annotator="Default" id="PMC1280409.nxml.gz-226" type="identity">
         <class id="incomplete_evidence"/>
         <span end="16651" id="PMC1280409.nxml.gz-227" start="16642">available</span>
      </annotation>
      <annotation annotator="Default" id="PMC1280409.nxml.gz-228" type="identity">
         <class id="may_be"/>
         <span end="17081" id="PMC1280409.nxml.gz-229" start="17075">may be</span>
      </annotation>
      <annotation annotator="Default" id="PMC1280409.nxml.gz-230" type="identity">
         <class id="believed"/>
         <span end="17511" id="PMC1280409.nxml.gz-231" start="17503">believed</span>
      </annotation>
      <annotation annotator="Default" id="PMC1280409.nxml.gz-232" type="identity">
         <class id="small"/>
         <span end="18180" id="PMC1280409.nxml.gz-233" start="18175">small</span>
      </annotation>
      <annotation annotator="Default" id="PMC1280409.nxml.gz-234" type="identity">
         <class id="limits"/>
         <span end="18241" id="PMC1280409.nxml.gz-235" start="18235">limits</span>
      </annotation>
      <annotation annotator="Default" id="PMC1280409.nxml.gz-236" type="identity">
         <class id="limitations"/>
         <span end="18269" id="PMC1280409.nxml.gz-237" start="18258">limitations</span>
      </annotation>
      <annotation annotator="Default" id="PMC1280409.nxml.gz-238" type="identity">
         <class id="observed"/>
         <span end="18378" id="PMC1280409.nxml.gz-239" start="18370">observed</span>
      </annotation>
      <annotation annotator="Default" id="PMC1280409.nxml.gz-240" type="identity">
         <class id="could_be"/>
         <span end="18404" id="PMC1280409.nxml.gz-241" start="18396">could be</span>
      </annotation>
      <annotation annotator="Default" id="PMC1280409.nxml.gz-242" type="identity">
         <class id="may_be"/>
         <span end="18506" id="PMC1280409.nxml.gz-243" start="18500">may be</span>
      </annotation>
      <annotation annotator="Default" id="PMC1280409.nxml.gz-244" type="identity">
         <class id="incomplete_evidence"/>
         <span end="18555" id="PMC1280409.nxml.gz-245" start="18549">models</span>
      </annotation>
      <annotation annotator="Default" id="PMC1280409.nxml.gz-246" type="identity">
         <class id="has_been_shown"/>
         <span end="18577" id="PMC1280409.nxml.gz-247" start="18563">has been shown</span>
      </annotation>
      <annotation annotator="Default" id="PMC1280409.nxml.gz-248" type="identity">
         <class id="findings"/>
         <span end="18740" id="PMC1280409.nxml.gz-249" start="18732">findings</span>
      </annotation>
      <annotation annotator="Default" id="PMC1280409.nxml.gz-250" type="identity">
         <class id="small"/>
         <span end="18843" id="PMC1280409.nxml.gz-251" start="18838">small</span>
      </annotation>
      <annotation annotator="Default" id="PMC1280409.nxml.gz-252" type="identity">
         <class id="incomplete_evidence"/>
         <span end="19331" id="PMC1280409.nxml.gz-253" start="19319">less refined</span>
      </annotation>
      <annotation annotator="Default" id="PMC1280409.nxml.gz-254" type="identity">
         <class id="may"/>
         <span end="19397" id="PMC1280409.nxml.gz-255" start="19394">may</span>
      </annotation>
      <annotation annotator="Default" id="PMC1280409.nxml.gz-256" type="identity">
         <class id="incomplete_evidence"/>
         <span end="19629" id="PMC1280409.nxml.gz-257" start="19622">initial</span>
      </annotation>
      <annotation annotator="Default" id="PMC1280409.nxml.gz-258" type="identity">
         <class id="preliminary"/>
         <span end="19688" id="PMC1280409.nxml.gz-259" start="19677">preliminary</span>
      </annotation>
      <annotation annotator="Default" id="PMC1280409.nxml.gz-260" type="identity">
         <class id="describe"/>
         <span end="19719" id="PMC1280409.nxml.gz-261" start="19711">describe</span>
      </annotation>
      <annotation annotator="Default" id="PMC1280409.nxml.gz-262" type="identity">
         <class id="may_be"/>
         <span end="20040" id="PMC1280409.nxml.gz-263" start="20034">may be</span>
      </annotation>
      <annotation annotator="Default" id="PMC1280409.nxml.gz-264" type="identity">
         <class id="might"/>
         <span end="20092" id="PMC1280409.nxml.gz-265" start="20087">might</span>
      </annotation>
      <annotation annotator="Default" id="PMC1280409.nxml.gz-266" type="identity">
         <class id="limited"/>
         <span end="20512" id="PMC1280409.nxml.gz-267" start="20505">limited</span>
      </annotation>
      <annotation annotator="Default" id="PMC1280409.nxml.gz-268" type="identity">
         <class id="incomplete_evidence"/>
         <span end="20797" id="PMC1280409.nxml.gz-269" start="20791">models</span>
      </annotation>
      <annotation annotator="Default" id="PMC1280409.nxml.gz-270" type="identity">
         <class id="observations"/>
         <span end="20866" id="PMC1280409.nxml.gz-271" start="20854">observations</span>
      </annotation>
      <annotation annotator="Default" id="PMC1280409.nxml.gz-272" type="identity">
         <class id="incomplete_evidence"/>
         <span end="20906" id="PMC1280409.nxml.gz-273" start="20900">models</span>
      </annotation>
      <annotation annotator="Default" id="PMC1280409.nxml.gz-274" type="identity">
         <class id="some"/>
         <span end="20949" id="PMC1280409.nxml.gz-275" start="20945">some</span>
      </annotation>
      <annotation annotator="Default" id="PMC1280409.nxml.gz-276" type="identity">
         <class id="incomplete_evidence"/>
         <span end="21043" id="PMC1280409.nxml.gz-277" start="21037">models</span>
      </annotation>
      <annotation annotator="Default" id="PMC1280409.nxml.gz-278" type="identity">
         <class id="number_of"/>
         <span end="21109" id="PMC1280409.nxml.gz-279" start="21100">number of</span>
      </annotation>
      <annotation annotator="Default" id="PMC1280409.nxml.gz-280" type="identity">
         <class id="limitations"/>
         <span end="21121" id="PMC1280409.nxml.gz-281" start="21110">limitations</span>
      </annotation>
      <annotation annotator="Default" id="PMC1280409.nxml.gz-282" type="identity">
         <class id="believe"/>
         <span end="21232" id="PMC1280409.nxml.gz-283" start="21225">believe</span>
      </annotation>
      <annotation annotator="Default" id="PMC1280409.nxml.gz-284" type="identity">
         <class id="available_data"/>
         <span end="21316" id="PMC1280409.nxml.gz-285" start="21302">available data</span>
      </annotation>
      <annotation annotator="Default" id="PMC1280409.nxml.gz-286" type="identity">
         <class id="observational"/>
         <span end="21376" id="PMC1280409.nxml.gz-287" start="21363">observational</span>
      </annotation>
      <annotation annotator="Default" id="PMC1280409.nxml.gz-288" type="identity">
         <class id="findings"/>
         <span end="21402" id="PMC1280409.nxml.gz-289" start="21394">findings</span>
      </annotation>
      <annotation annotator="Default" id="PMC1280409.nxml.gz-290" type="identity">
         <class id="probable_understanding"/>
         <span end="1292" id="PMC1280409.nxml.gz-291" start="1283">theorized</span>
      </annotation>
      <annotation annotator="Default" id="PMC1280409.nxml.gz-292" type="identity">
         <class id="putative"/>
         <span end="4592" id="PMC1280409.nxml.gz-293" start="4584">putative</span>
      </annotation>
      <annotation annotator="Default" id="PMC1280409.nxml.gz-294" type="identity">
         <class id="likely"/>
         <span end="4858" id="PMC1280409.nxml.gz-295" start="4852">likely</span>
      </annotation>
      <annotation annotator="Default" id="PMC1280409.nxml.gz-296" type="identity">
         <class id="as"/>
         <span end="7936" id="PMC1280409.nxml.gz-297" start="7934">As</span>
      </annotation>
      <annotation annotator="Default" id="PMC1280409.nxml.gz-298" type="identity">
         <class id="typically"/>
         <span end="9557" id="PMC1280409.nxml.gz-299" start="9548">typically</span>
      </annotation>
      <annotation annotator="Default" id="PMC1280409.nxml.gz-300" type="identity">
         <class id="probable_understanding"/>
         <span end="9657" id="PMC1280409.nxml.gz-301" start="9647">represents</span>
      </annotation>
      <annotation annotator="Default" id="PMC1280409.nxml.gz-302" type="identity">
         <class id="explain"/>
         <span end="10044" id="PMC1280409.nxml.gz-303" start="10037">explain</span>
      </annotation>
      <annotation annotator="Default" id="PMC1280409.nxml.gz-304" type="identity">
         <class id="probable_understanding"/>
         <span end="11295" id="PMC1280409.nxml.gz-305" start="11288">because</span>
      </annotation>
      <annotation annotator="Default" id="PMC1280409.nxml.gz-306" type="identity">
         <class id="generally"/>
         <span end="13178" id="PMC1280409.nxml.gz-307" start="13169">generally</span>
      </annotation>
      <annotation annotator="Default" id="PMC1280409.nxml.gz-308" type="identity">
         <class id="likely"/>
         <span end="17405" id="PMC1280409.nxml.gz-309" start="17399">likely</span>
      </annotation>
      <annotation annotator="Default" id="PMC1280409.nxml.gz-310" type="identity">
         <class id="probable_understanding"/>
         <span end="18360" id="PMC1280409.nxml.gz-311" start="18355">means</span>
      </annotation>
      <annotation annotator="Default" id="PMC1280409.nxml.gz-312" type="identity">
         <class id="proven"/>
         <span end="19161" id="PMC1280409.nxml.gz-313" start="19155">proven</span>
      </annotation>
      <annotation annotator="Default" id="PMC1280409.nxml.gz-314" type="identity">
         <class id="probable_understanding"/>
         <span end="20728" id="PMC1280409.nxml.gz-315" start="20722">nearly</span>
      </annotation>
      <annotation annotator="Default" id="PMC1280409.nxml.gz-316" type="identity">
         <class id="related"/>
         <span end="71" id="PMC1280409.nxml.gz-317" start="64">related</span>
      </annotation>
      <annotation annotator="Default" id="PMC1280409.nxml.gz-318" type="identity">
         <class id="factors"/>
         <span end="513" id="PMC1280409.nxml.gz-319" start="506">factors</span>
      </annotation>
      <annotation annotator="Default" id="PMC1280409.nxml.gz-320" type="identity">
         <class id="effects"/>
         <span end="657" id="PMC1280409.nxml.gz-321" start="650">effects</span>
      </annotation>
      <annotation annotator="Default" id="PMC1280409.nxml.gz-322" type="identity">
         <class id="associated"/>
         <span end="1173" id="PMC1280409.nxml.gz-323" start="1163">associated</span>
      </annotation>
      <annotation annotator="Default" id="PMC1280409.nxml.gz-324" type="identity">
         <class id="interactions"/>
         <span end="1517" id="PMC1280409.nxml.gz-325" start="1505">interactions</span>
      </annotation>
      <annotation annotator="Default" id="PMC1280409.nxml.gz-326" type="identity">
         <class id="underlying"/>
         <span end="1769" id="PMC1280409.nxml.gz-327" start="1759">underlying</span>
      </annotation>
      <annotation annotator="Default" id="PMC1280409.nxml.gz-328" type="identity">
         <class id="relationship"/>
         <span end="1944" id="PMC1280409.nxml.gz-329" start="1932">relationship</span>
      </annotation>
      <annotation annotator="Default" id="PMC1280409.nxml.gz-330" type="identity">
         <class id="underlying"/>
         <span end="2426" id="PMC1280409.nxml.gz-331" start="2416">underlying</span>
      </annotation>
      <annotation annotator="Default" id="PMC1280409.nxml.gz-332" type="identity">
         <class id="underlying"/>
         <span end="3768" id="PMC1280409.nxml.gz-333" start="3758">underlying</span>
      </annotation>
      <annotation annotator="Default" id="PMC1280409.nxml.gz-334" type="identity">
         <class id="factor"/>
         <span end="4848" id="PMC1280409.nxml.gz-335" start="4842">factor</span>
      </annotation>
      <annotation annotator="Default" id="PMC1280409.nxml.gz-336" type="identity">
         <class id="contribute"/>
         <span end="4872" id="PMC1280409.nxml.gz-337" start="4862">contribute</span>
      </annotation>
      <annotation annotator="Default" id="PMC1280409.nxml.gz-338" type="identity">
         <class id="risk_factor"/>
         <span end="5657" id="PMC1280409.nxml.gz-339" start="5646">risk factor</span>
      </annotation>
      <annotation annotator="Default" id="PMC1280409.nxml.gz-340" type="identity">
         <class id="markers"/>
         <span end="7068" id="PMC1280409.nxml.gz-341" start="7061">markers</span>
      </annotation>
      <annotation annotator="Default" id="PMC1280409.nxml.gz-342" type="identity">
         <class id="associations"/>
         <span end="7120" id="PMC1280409.nxml.gz-343" start="7108">associations</span>
      </annotation>
      <annotation annotator="Default" id="PMC1280409.nxml.gz-344" type="identity">
         <class id="proxy"/>
         <span end="8056" id="PMC1280409.nxml.gz-345" start="8051">proxy</span>
      </annotation>
      <annotation annotator="Default" id="PMC1280409.nxml.gz-346" type="identity">
         <class id="associated"/>
         <span end="8249" id="PMC1280409.nxml.gz-347" start="8239">associated</span>
      </annotation>
      <annotation annotator="Default" id="PMC1280409.nxml.gz-348" type="identity">
         <class id="superficial_relationship"/>
         <span end="8973" id="PMC1280409.nxml.gz-349" start="8964">conferred</span>
      </annotation>
      <annotation annotator="Default" id="PMC1280409.nxml.gz-350" type="identity">
         <class id="association"/>
         <span end="9409" id="PMC1280409.nxml.gz-351" start="9398">association</span>
      </annotation>
      <annotation annotator="Default" id="PMC1280409.nxml.gz-352" type="identity">
         <class id="association"/>
         <span end="9506" id="PMC1280409.nxml.gz-353" start="9495">association</span>
      </annotation>
      <annotation annotator="Default" id="PMC1280409.nxml.gz-354" type="identity">
         <class id="represents"/>
         <span end="9657" id="PMC1280409.nxml.gz-355" start="9647">represents</span>
      </annotation>
      <annotation annotator="Default" id="PMC1280409.nxml.gz-356" type="identity">
         <class id="proxy"/>
         <span end="9665" id="PMC1280409.nxml.gz-357" start="9660">proxy</span>
      </annotation>
      <annotation annotator="Default" id="PMC1280409.nxml.gz-358" type="identity">
         <class id="associated"/>
         <span end="9878" id="PMC1280409.nxml.gz-359" start="9868">associated</span>
      </annotation>
      <annotation annotator="Default" id="PMC1280409.nxml.gz-360" type="identity">
         <class id="role"/>
         <span end="10171" id="PMC1280409.nxml.gz-361" start="10167">role</span>
      </annotation>
      <annotation annotator="Default" id="PMC1280409.nxml.gz-362" type="identity">
         <class id="implicated"/>
         <span end="10310" id="PMC1280409.nxml.gz-363" start="10300">implicated</span>
      </annotation>
      <annotation annotator="Default" id="PMC1280409.nxml.gz-364" type="identity">
         <class id="superficial_relationship"/>
         <span end="10789" id="PMC1280409.nxml.gz-365" start="10780">conferred</span>
      </annotation>
      <annotation annotator="Default" id="PMC1280409.nxml.gz-366" type="identity">
         <class id="associated"/>
         <span end="11153" id="PMC1280409.nxml.gz-367" start="11143">associated</span>
      </annotation>
      <annotation annotator="Default" id="PMC1280409.nxml.gz-368" type="identity">
         <class id="associated"/>
         <span end="11644" id="PMC1280409.nxml.gz-369" start="11634">associated</span>
      </annotation>
      <annotation annotator="Default" id="PMC1280409.nxml.gz-370" type="identity">
         <class id="independent"/>
         <span end="11781" id="PMC1280409.nxml.gz-371" start="11770">independent</span>
      </annotation>
      <annotation annotator="Default" id="PMC1280409.nxml.gz-372" type="identity">
         <class id="effects"/>
         <span end="12051" id="PMC1280409.nxml.gz-373" start="12044">effects</span>
      </annotation>
      <annotation annotator="Default" id="PMC1280409.nxml.gz-374" type="identity">
         <class id="role"/>
         <span end="13220" id="PMC1280409.nxml.gz-375" start="13216">role</span>
      </annotation>
      <annotation annotator="Default" id="PMC1280409.nxml.gz-376" type="identity">
         <class id="associated"/>
         <span end="14149" id="PMC1280409.nxml.gz-377" start="14139">associated</span>
      </annotation>
      <annotation annotator="Default" id="PMC1280409.nxml.gz-378" type="identity">
         <class id="similar"/>
         <span end="14401" id="PMC1280409.nxml.gz-379" start="14394">similar</span>
      </annotation>
      <annotation annotator="Default" id="PMC1280409.nxml.gz-380" type="identity">
         <class id="predictors"/>
         <span end="15300" id="PMC1280409.nxml.gz-381" start="15290">predictors</span>
      </annotation>
      <annotation annotator="Default" id="PMC1280409.nxml.gz-382" type="identity">
         <class id="associated"/>
         <span end="15366" id="PMC1280409.nxml.gz-383" start="15356">associated</span>
      </annotation>
      <annotation annotator="Default" id="PMC1280409.nxml.gz-384" type="identity">
         <class id="related"/>
         <span end="15619" id="PMC1280409.nxml.gz-385" start="15612">related</span>
      </annotation>
      <annotation annotator="Default" id="PMC1280409.nxml.gz-386" type="identity">
         <class id="effects"/>
         <span end="15822" id="PMC1280409.nxml.gz-387" start="15815">effects</span>
      </annotation>
      <annotation annotator="Default" id="PMC1280409.nxml.gz-388" type="identity">
         <class id="similarly"/>
         <span end="16021" id="PMC1280409.nxml.gz-389" start="16012">Similarly</span>
      </annotation>
      <annotation annotator="Default" id="PMC1280409.nxml.gz-390" type="identity">
         <class id="associated"/>
         <span end="16087" id="PMC1280409.nxml.gz-391" start="16077">associated</span>
      </annotation>
      <annotation annotator="Default" id="PMC1280409.nxml.gz-392" type="identity">
         <class id="superficial_relationship"/>
         <span end="16161" id="PMC1280409.nxml.gz-393" start="16157">risk</span>
      </annotation>
      <annotation annotator="Default" id="PMC1280409.nxml.gz-394" type="identity">
         <class id="relate"/>
         <span end="16563" id="PMC1280409.nxml.gz-395" start="16557">relate</span>
      </annotation>
      <annotation annotator="Default" id="PMC1280409.nxml.gz-396" type="identity">
         <class id="predictive"/>
         <span end="17261" id="PMC1280409.nxml.gz-397" start="17251">predictive</span>
      </annotation>
      <annotation annotator="Default" id="PMC1280409.nxml.gz-398" type="identity">
         <class id="indicator"/>
         <span end="17430" id="PMC1280409.nxml.gz-399" start="17421">indicator</span>
      </annotation>
      <annotation annotator="Default" id="PMC1280409.nxml.gz-400" type="identity">
         <class id="associated"/>
         <span end="18053" id="PMC1280409.nxml.gz-401" start="18043">associated</span>
      </annotation>
      <annotation annotator="Default" id="PMC1280409.nxml.gz-402" type="identity">
         <class id="mediated"/>
         <span end="18413" id="PMC1280409.nxml.gz-403" start="18405">mediated</span>
      </annotation>
      <annotation annotator="Default" id="PMC1280409.nxml.gz-404" type="identity">
         <class id="effects"/>
         <span end="18428" id="PMC1280409.nxml.gz-405" start="18421">effects</span>
      </annotation>
      <annotation annotator="Default" id="PMC1280409.nxml.gz-406" type="identity">
         <class id="relationships"/>
         <span end="19225" id="PMC1280409.nxml.gz-407" start="19212">relationships</span>
      </annotation>
      <annotation annotator="Default" id="PMC1280409.nxml.gz-408" type="identity">
         <class id="roles"/>
         <span end="20161" id="PMC1280409.nxml.gz-409" start="20156">roles</span>
      </annotation>
      <annotation annotator="Default" id="PMC1280409.nxml.gz-410" type="identity">
         <class id="effects"/>
         <span end="20327" id="PMC1280409.nxml.gz-411" start="20320">effects</span>
      </annotation>
      <annotation annotator="Default" id="PMC1280409.nxml.gz-412" type="identity">
         <class id="links"/>
         <span end="20687" id="PMC1280409.nxml.gz-413" start="20682">links</span>
      </annotation>
      <annotation annotator="Default" id="PMC1280409.nxml.gz-414" type="identity">
         <class id="implicated"/>
         <span end="20977" id="PMC1280409.nxml.gz-415" start="20967">implicated</span>
      </annotation>
      <annotation annotator="Default" id="PMC1280409.nxml.gz-416" type="identity">
         <class id="effective"/>
         <span end="21268" id="PMC1280409.nxml.gz-417" start="21259">effective</span>
      </annotation>
      <annotation annotator="Default" id="PMC1280409.nxml.gz-418" type="identity">
         <class id="prevention"/>
         <span end="21279" id="PMC1280409.nxml.gz-419" start="21269">prevention</span>
      </annotation>
      <annotation annotator="Default" id="PMC1280409.nxml.gz-420" type="identity">
         <class id="role"/>
         <span end="21594" id="PMC1280409.nxml.gz-421" start="21590">role</span>
      </annotation>
      <annotation annotator="Default" id="PMC1280409.nxml.gz-422" type="identity">
         <class id="opportunities"/>
         <span end="922" id="PMC1280409.nxml.gz-423" start="909">opportunities</span>
      </annotation>
      <annotation annotator="Default" id="PMC1280409.nxml.gz-424" type="identity">
         <class id="investigations"/>
         <span end="4359" id="PMC1280409.nxml.gz-425" start="4345">investigations</span>
      </annotation>
      <annotation annotator="Default" id="PMC1280409.nxml.gz-426" type="identity">
         <class id="investigations"/>
         <span end="4436" id="PMC1280409.nxml.gz-427" start="4422">investigations</span>
      </annotation>
      <annotation annotator="Default" id="PMC1280409.nxml.gz-428" type="identity">
         <class id="future_work"/>
         <span end="4764" id="PMC1280409.nxml.gz-429" start="4756">required</span>
      </annotation>
      <annotation annotator="Default" id="PMC1280409.nxml.gz-430" type="identity">
         <class id="future_studies"/>
         <span end="6164" id="PMC1280409.nxml.gz-431" start="6150">future studies</span>
      </annotation>
      <annotation annotator="Default" id="PMC1280409.nxml.gz-432" type="identity">
         <class id="future_work"/>
         <span end="10024" id="PMC1280409.nxml.gz-433" start="10000">Further investigation is</span>
      </annotation>
      <annotation annotator="Default" id="PMC1280409.nxml.gz-434" type="identity">
         <class id="should_be"/>
         <span end="18279" id="PMC1280409.nxml.gz-435" start="18270">should be</span>
      </annotation>
      <annotation annotator="Default" id="PMC1280409.nxml.gz-436" type="identity">
         <class id="future_directions"/>
         <span end="19060" id="PMC1280409.nxml.gz-437" start="19043">Future Directions</span>
      </annotation>
      <annotation annotator="Default" id="PMC1280409.nxml.gz-438" type="identity">
         <class id="investigations"/>
         <span end="19388" id="PMC1280409.nxml.gz-439" start="19374">investigations</span>
      </annotation>
      <annotation annotator="Default" id="PMC1280409.nxml.gz-440" type="identity">
         <class id="future_work"/>
         <span end="20040" id="PMC1280409.nxml.gz-441" start="20038">be</span>
      </annotation>
      <annotation annotator="Default" id="PMC1280409.nxml.gz-442" type="identity">
         <class id="future_work"/>
         <span end="20061" id="PMC1280409.nxml.gz-443" start="20041">further investigated</span>
      </annotation>
      <annotation annotator="Default" id="PMC1280409.nxml.gz-444" type="identity">
         <class id="considered"/>
         <span end="20373" id="PMC1280409.nxml.gz-445" start="20363">considered</span>
      </annotation>
      <annotation annotator="Default" id="PMC1280409.nxml.gz-446" type="identity">
         <class id="future"/>
         <span end="21608" id="PMC1280409.nxml.gz-447" start="21602">future</span>
      </annotation>
      <annotation annotator="Default" id="PMC1280409.nxml.gz-448" type="identity">
         <class id="important_consideration"/>
         <span end="1927" id="PMC1280409.nxml.gz-449" start="1915">particularly</span>
      </annotation>
      <annotation annotator="Default" id="PMC1280409.nxml.gz-450" type="identity">
         <class id="key"/>
         <span end="4341" id="PMC1280409.nxml.gz-451" start="4338">key</span>
      </annotation>
      <annotation annotator="Default" id="PMC1280409.nxml.gz-452" type="identity">
         <class id="important_consideration"/>
         <span end="4688" id="PMC1280409.nxml.gz-453" start="4681">must be</span>
      </annotation>
      <annotation annotator="Default" id="PMC1280409.nxml.gz-454" type="identity">
         <class id="required"/>
         <span end="4764" id="PMC1280409.nxml.gz-455" start="4756">required</span>
      </annotation>
      <annotation annotator="Default" id="PMC1280409.nxml.gz-456" type="identity">
         <class id="key"/>
         <span end="9206" id="PMC1280409.nxml.gz-457" start="9203">key</span>
      </annotation>
      <annotation annotator="Default" id="PMC1280409.nxml.gz-458" type="identity">
         <class id="required"/>
         <span end="9290" id="PMC1280409.nxml.gz-459" start="9282">required</span>
      </annotation>
      <annotation annotator="Default" id="PMC1280409.nxml.gz-460" type="identity">
         <class id="risk"/>
         <span end="9901" id="PMC1280409.nxml.gz-461" start="9897">risk</span>
      </annotation>
      <annotation annotator="Default" id="PMC1280409.nxml.gz-462" type="identity">
         <class id="severe"/>
         <span end="10564" id="PMC1280409.nxml.gz-463" start="10558">severe</span>
      </annotation>
      <annotation annotator="Default" id="PMC1280409.nxml.gz-464" type="identity">
         <class id="important_consideration"/>
         <span end="11276" id="PMC1280409.nxml.gz-465" start="11271">focus</span>
      </annotation>
      <annotation annotator="Default" id="PMC1280409.nxml.gz-466" type="identity">
         <class id="serious"/>
         <span end="12148" id="PMC1280409.nxml.gz-467" start="12141">serious</span>
      </annotation>
      <annotation annotator="Default" id="PMC1280409.nxml.gz-468" type="identity">
         <class id="important_consideration"/>
         <span end="12161" id="PMC1280409.nxml.gz-469" start="12149">consequences</span>
      </annotation>
      <annotation annotator="Default" id="PMC1280409.nxml.gz-470" type="identity">
         <class id="important_consideration"/>
         <span end="12201" id="PMC1280409.nxml.gz-471" start="12192">disproved</span>
      </annotation>
      <annotation annotator="Default" id="PMC1280409.nxml.gz-472" type="identity">
         <class id="serious"/>
         <span end="12465" id="PMC1280409.nxml.gz-473" start="12458">serious</span>
      </annotation>
      <annotation annotator="Default" id="PMC1280409.nxml.gz-474" type="identity">
         <class id="important"/>
         <span end="18257" id="PMC1280409.nxml.gz-475" start="18248">important</span>
      </annotation>
      <annotation annotator="Default" id="PMC1280409.nxml.gz-476" type="identity">
         <class id="still"/>
         <span end="19676" id="PMC1280409.nxml.gz-477" start="19671">still</span>
      </annotation>
      <annotation annotator="Default" id="PMC1280409.nxml.gz-478" type="identity">
         <class id="benefit"/>
         <span end="19792" id="PMC1280409.nxml.gz-479" start="19785">benefit</span>
      </annotation>
      <annotation annotator="Default" id="PMC1280409.nxml.gz-480" type="identity">
         <class id="important"/>
         <span end="20489" id="PMC1280409.nxml.gz-481" start="20480">important</span>
      </annotation>
      <annotation annotator="Default" id="PMC1280409.nxml.gz-482" type="identity">
         <class id="important_consideration"/>
         <span end="21255" id="PMC1280409.nxml.gz-483" start="21251">goal</span>
      </annotation>
      <annotation annotator="Default" id="PMC1280409.nxml.gz-484" type="identity">
         <class id="important_consideration"/>
         <span end="21340" id="PMC1280409.nxml.gz-485" start="21333">must be</span>
      </annotation>
      <annotation annotator="Default" id="PMC1280409.nxml.gz-486" type="identity">
         <class id="crucial"/>
         <span end="21589" id="PMC1280409.nxml.gz-487" start="21582">crucial</span>
      </annotation>
      <annotation annotator="Default" id="PMC1280409.nxml.gz-488" type="identity">
         <class id="seemed"/>
         <span end="3016" id="PMC1280409.nxml.gz-489" start="3010">seemed</span>
      </annotation>
      <annotation annotator="Default" id="PMC1280409.nxml.gz-490" type="identity">
         <class id="although"/>
         <span end="3115" id="PMC1280409.nxml.gz-491" start="3107">Although</span>
      </annotation>
      <annotation annotator="Default" id="PMC1280409.nxml.gz-492" type="identity">
         <class id="noted"/>
         <span end="3248" id="PMC1280409.nxml.gz-493" start="3243">noted</span>
      </annotation>
      <annotation annotator="Default" id="PMC1280409.nxml.gz-494" type="identity">
         <class id="although"/>
         <span end="8393" id="PMC1280409.nxml.gz-495" start="8385">although</span>
      </annotation>
      <annotation annotator="Default" id="PMC1280409.nxml.gz-496" type="identity">
         <class id="anomaly_curious_finding"/>
         <span end="9008" id="PMC1280409.nxml.gz-497" start="9001">whereas</span>
      </annotation>
      <annotation annotator="Default" id="PMC1280409.nxml.gz-498" type="identity">
         <class id="although"/>
         <span end="9139" id="PMC1280409.nxml.gz-499" start="9131">Although</span>
      </annotation>
      <annotation annotator="Default" id="PMC1280409.nxml.gz-500" type="identity">
         <class id="although"/>
         <span end="9367" id="PMC1280409.nxml.gz-501" start="9359">Although</span>
      </annotation>
      <annotation annotator="Default" id="PMC1280409.nxml.gz-502" type="identity">
         <class id="anomaly_curious_finding"/>
         <span end="12305" id="PMC1280409.nxml.gz-503" start="12297">not only</span>
      </annotation>
      <annotation annotator="Default" id="PMC1280409.nxml.gz-504" type="identity">
         <class id="anomaly_curious_finding"/>
         <span end="12337" id="PMC1280409.nxml.gz-505" start="12329">but also</span>
      </annotation>
      <annotation annotator="Default" id="PMC1280409.nxml.gz-506" type="identity">
         <class id="although"/>
         <span end="12382" id="PMC1280409.nxml.gz-507" start="12374">Although</span>
      </annotation>
      <annotation annotator="Default" id="PMC1280409.nxml.gz-508" type="identity">
         <class id="although"/>
         <span end="14117" id="PMC1280409.nxml.gz-509" start="14109">although</span>
      </annotation>
      <annotation annotator="Default" id="PMC1280409.nxml.gz-510" type="identity">
         <class id="although"/>
         <span end="15695" id="PMC1280409.nxml.gz-511" start="15687">although</span>
      </annotation>
      <annotation annotator="Default" id="PMC1280409.nxml.gz-512" type="identity">
         <class id="although"/>
         <span end="16188" id="PMC1280409.nxml.gz-513" start="16180">Although</span>
      </annotation>
      <annotation annotator="Default" id="PMC1280409.nxml.gz-514" type="identity">
         <class id="alternative_options_controversy"/>
         <span end="1292" id="PMC1280409.nxml.gz-515" start="1283">theorized</span>
      </annotation>
      <annotation annotator="Default" id="PMC1280409.nxml.gz-516" type="identity">
         <class id="alternative_options_controversy"/>
         <span end="1710" id="PMC1280409.nxml.gz-517" start="1702">Although</span>
      </annotation>
      <annotation annotator="Default" id="PMC1280409.nxml.gz-518" type="identity">
         <class id="debate"/>
         <span end="1814" id="PMC1280409.nxml.gz-519" start="1808">debate</span>
      </annotation>
      <annotation annotator="Default" id="PMC1280409.nxml.gz-520" type="identity">
         <class id="doubt"/>
         <span end="2388" id="PMC1280409.nxml.gz-521" start="2383">doubt</span>
      </annotation>
      <annotation annotator="Default" id="PMC1280409.nxml.gz-522" type="identity">
         <class id="but"/>
         <span end="2494" id="PMC1280409.nxml.gz-523" start="2491">but</span>
      </annotation>
      <annotation annotator="Default" id="PMC1280409.nxml.gz-524" type="identity">
         <class id="alternative_options_controversy"/>
         <span end="2512" id="PMC1280409.nxml.gz-525" start="2500">unsuccessful</span>
      </annotation>
      <annotation annotator="Default" id="PMC1280409.nxml.gz-526" type="identity">
         <class id="differences"/>
         <span end="2885" id="PMC1280409.nxml.gz-527" start="2874">differences</span>
      </annotation>
      <annotation annotator="Default" id="PMC1280409.nxml.gz-528" type="identity">
         <class id="whether"/>
         <span end="3733" id="PMC1280409.nxml.gz-529" start="3726">whether</span>
      </annotation>
      <annotation annotator="Default" id="PMC1280409.nxml.gz-530" type="identity">
         <class id="rather"/>
         <span end="3787" id="PMC1280409.nxml.gz-531" start="3781">rather</span>
      </annotation>
      <annotation annotator="Default" id="PMC1280409.nxml.gz-532" type="identity">
         <class id="however"/>
         <span end="4415" id="PMC1280409.nxml.gz-533" start="4408">However</span>
      </annotation>
      <annotation annotator="Default" id="PMC1280409.nxml.gz-534" type="identity">
         <class id="alternative_options_controversy"/>
         <span end="5252" id="PMC1280409.nxml.gz-535" start="5245">Various</span>
      </annotation>
      <annotation annotator="Default" id="PMC1280409.nxml.gz-536" type="identity">
         <class id="hypotheses"/>
         <span end="5263" id="PMC1280409.nxml.gz-537" start="5253">hypotheses</span>
      </annotation>
      <annotation annotator="Default" id="PMC1280409.nxml.gz-538" type="identity">
         <class id="however"/>
         <span end="8383" id="PMC1280409.nxml.gz-539" start="8376">However</span>
      </annotation>
      <annotation annotator="Default" id="PMC1280409.nxml.gz-540" type="identity">
         <class id="alternative_options_controversy"/>
         <span end="8393" id="PMC1280409.nxml.gz-541" start="8385">although</span>
      </annotation>
      <annotation annotator="Default" id="PMC1280409.nxml.gz-542" type="identity">
         <class id="whereas"/>
         <span end="9008" id="PMC1280409.nxml.gz-543" start="9001">whereas</span>
      </annotation>
      <annotation annotator="Default" id="PMC1280409.nxml.gz-544" type="identity">
         <class id="alternative_options_controversy"/>
         <span end="9139" id="PMC1280409.nxml.gz-545" start="9131">Although</span>
      </annotation>
      <annotation annotator="Default" id="PMC1280409.nxml.gz-546" type="identity">
         <class id="whereas"/>
         <span end="9910" id="PMC1280409.nxml.gz-547" start="9903">whereas</span>
      </annotation>
      <annotation annotator="Default" id="PMC1280409.nxml.gz-548" type="identity">
         <class id="difference"/>
         <span end="10060" id="PMC1280409.nxml.gz-549" start="10050">difference</span>
      </annotation>
      <annotation annotator="Default" id="PMC1280409.nxml.gz-550" type="identity">
         <class id="whereas"/>
         <span end="10821" id="PMC1280409.nxml.gz-551" start="10814">whereas</span>
      </annotation>
      <annotation annotator="Default" id="PMC1280409.nxml.gz-552" type="identity">
         <class id="rather"/>
         <span end="11235" id="PMC1280409.nxml.gz-553" start="11229">rather</span>
      </annotation>
      <annotation annotator="Default" id="PMC1280409.nxml.gz-554" type="identity">
         <class id="however"/>
         <span end="13289" id="PMC1280409.nxml.gz-555" start="13282">However</span>
      </annotation>
      <annotation annotator="Default" id="PMC1280409.nxml.gz-556" type="identity">
         <class id="alternative_options_controversy"/>
         <span end="16618" id="PMC1280409.nxml.gz-557" start="16610">Although</span>
      </annotation>
      <annotation annotator="Default" id="PMC1280409.nxml.gz-558" type="identity">
         <class id="however"/>
         <span end="17009" id="PMC1280409.nxml.gz-559" start="17002">However</span>
      </annotation>
      <annotation annotator="Default" id="PMC1280409.nxml.gz-560" type="identity">
         <class id="rather"/>
         <span end="18329" id="PMC1280409.nxml.gz-561" start="18323">rather</span>
      </annotation>
      <annotation annotator="Default" id="PMC1280409.nxml.gz-562" type="identity">
         <class id="rather"/>
         <span end="18450" id="PMC1280409.nxml.gz-563" start="18444">rather</span>
      </annotation>
      <annotation annotator="Default" id="PMC1280409.nxml.gz-564" type="identity">
         <class id="problematic"/>
         <span end="3637" id="PMC1280409.nxml.gz-565" start="3626">problematic</span>
      </annotation>
      <annotation annotator="Default" id="PMC1280409.nxml.gz-566" type="identity">
         <class id="because"/>
         <span end="3696" id="PMC1280409.nxml.gz-567" start="3689">because</span>
      </annotation>
      <annotation annotator="Default" id="PMC1280409.nxml.gz-568" type="identity">
         <class id="because"/>
         <span end="3754" id="PMC1280409.nxml.gz-569" start="3747">because</span>
      </annotation>
      <annotation annotator="Default" id="PMC1280409.nxml.gz-570" type="identity">
         <class id="because"/>
         <span end="3989" id="PMC1280409.nxml.gz-571" start="3982">because</span>
      </annotation>
      <annotation annotator="Default" id="PMC1280409.nxml.gz-572" type="identity">
         <class id="problem_complication"/>
         <span end="9218" id="PMC1280409.nxml.gz-573" start="9207">limitations</span>
      </annotation>
      <annotation annotator="Default" id="PMC1280409.nxml.gz-574" type="identity">
         <class id="concern"/>
         <span end="11287" id="PMC1280409.nxml.gz-575" start="11280">concern</span>
      </annotation>
      <annotation annotator="Default" id="PMC1280409.nxml.gz-576" type="identity">
         <class id="because"/>
         <span end="11295" id="PMC1280409.nxml.gz-577" start="11288">because</span>
      </annotation>
      <annotation annotator="Default" id="PMC1280409.nxml.gz-578" type="identity">
         <class id="because"/>
         <span end="13298" id="PMC1280409.nxml.gz-579" start="13291">because</span>
      </annotation>
      <annotation annotator="Default" id="PMC1280409.nxml.gz-580" type="identity">
         <class id="because"/>
         <span end="18807" id="PMC1280409.nxml.gz-581" start="18800">because</span>
      </annotation>
      <annotation annotator="Default" id="PMC1280409.nxml.gz-582" type="identity">
         <class id="problem_complication"/>
         <span end="21082" id="PMC1280409.nxml.gz-583" start="21073">imperfect</span>
      </annotation>
      <annotation annotator="Default" id="PMC1280409.nxml.gz-584" type="identity">
         <class id="problem_complication"/>
         <span end="21121" id="PMC1280409.nxml.gz-585" start="21110">limitations</span>
      </annotation>
      <annotation annotator="Default" id="PMC1280409.nxml.gz-586" type="identity">
         <class id="this_review"/>
         <span end="1830" id="PMC1280409.nxml.gz-587" start="1819">this review</span>
      </annotation>
      <annotation annotator="Default" id="PMC1280409.nxml.gz-588" type="identity">
         <class id="sought"/>
         <span end="8045" id="PMC1280409.nxml.gz-589" start="8039">sought</span>
      </annotation>
      <annotation annotator="Default" id="PMC1280409.nxml.gz-590" type="identity">
         <class id="here"/>
         <span end="8620" id="PMC1280409.nxml.gz-591" start="8616">here</span>
      </annotation>
      <annotation annotator="Default" id="PMC1280409.nxml.gz-592" type="identity">
         <class id="here"/>
         <span end="16240" id="PMC1280409.nxml.gz-593" start="16236">here</span>
      </annotation>
      <annotation annotator="Default" id="PMC1280409.nxml.gz-594" type="identity">
         <class id="to_assess"/>
         <span end="17234" id="PMC1280409.nxml.gz-595" start="17225">to assess</span>
      </annotation>
   </document>
</knowtator-project>
